easyeasy/__init__.py
easyeasy/client.py
easyeasy-1.0.2.dist-info/METADATA
easyeasy-1.0.2.dist-info/WHEEL
easyeasy-1.0.2.dist-info/top_level.txt
easyeasy-1.0.2.dist-info/RECORD
