Metadata-Version: 2.1
Name: easyeasy
Version: 1.0.2
Summary: Client for EasyEasy.io cloud database
Home-page: https://github.com/EasyEasyio/python-client
Author: EasyEasy.io
Author-email: feedback@easyeasy.io
License: UNKNOWN
Platform: UNKNOWN
Classifier: Programming Language :: Python :: 3
Classifier: License :: OSI Approved :: ISC License (ISCL)
Classifier: Operating System :: OS Independent
